{
  "main": {
    "id": "f09d6a27fb509a15",
    "type": "split",
    "children": [
      {
        "id": "af9c1e305e3ef770",
        "type": "tabs",
        "children": [
          {
            "id": "bcdda5e4074ac443",
            "type": "leaf",
            "pinned": true,
            "state": {
              "type": "markdown",
              "state": {
                "file": "04-Javascript/00-卡片/JavaScript卡片.md",
                "mode": "source",
                "backlinks": false,
                "source": false
              },
              "pinned": true
            }
          },
          {
            "id": "dd6158f7b4703975",
            "type": "leaf",
            "pinned": true,
            "state": {
              "type": "markdown",
              "state": {
                "file": "Vue.js 3.0企业级管理后台开发实战/Vue.js 3.0企业级管理后台开发实战：基于Element Plus.md",
                "mode": "source",
                "backlinks": false,
                "source": false
              },
              "pinned": true
            }
          },
          {
            "id": "db07be963cb8d17a",
            "type": "leaf",
            "pinned": true,
            "state": {
              "type": "markdown",
              "state": {
                "file": "Vue.js 3.0企业级管理后台开发实战/3.6 项目初始化配置.md",
                "mode": "source",
                "backlinks": false,
                "source": false
              },
              "pinned": true
            }
          },
          {
            "id": "b7325024ef8b77dc",
            "type": "leaf",
            "state": {
              "type": "markdown",
              "state": {
                "file": "0-前端视频记录/14-慕课/Vue组件库.md",
                "mode": "source",
                "backlinks": false,
                "source": false
              }
            }
          },
          {
            "id": "91f07b096b9f1268",
            "type": "leaf",
            "state": {
              "type": "markdown",
              "state": {
                "file": "H-每日记录/2024-04-20.md",
                "mode": "source",
                "backlinks": false,
                "source": false
              }
            }
          },
          {
            "id": "7a7f1964e384a557",
            "type": "leaf",
            "state": {
              "type": "markdown",
              "state": {
                "file": "H-每日记录/2024-04-20/遇见自然：无限人生书单第七季【完结】.md",
                "mode": "source",
                "backlinks": false,
                "source": false
              }
            }
          },
          {
            "id": "d1a7f8bcab29c46e",
            "type": "leaf",
            "state": {
              "type": "markdown",
              "state": {
                "file": "H-每日记录/2024-04-20/JavaScript 可视化：Promise.md",
                "mode": "source",
                "backlinks": false,
                "source": false
              }
            }
          },
          {
            "id": "87cb57d9ef219a00",
            "type": "leaf",
            "state": {
              "type": "markdown",
              "state": {
                "file": "H-每日记录/2024-04-20/遇见自然：无限人生书单第七季【完结】.md",
                "mode": "source",
                "backlinks": false,
                "source": false
              }
            }
          },
          {
            "id": "353706c2a29b4204",
            "type": "leaf",
            "state": {
              "type": "markdown",
              "state": {
                "file": "14-Git 和 Github/0-卡片/0-卡片.md",
                "mode": "source",
                "backlinks": false,
                "source": false
              }
            }
          },
          {
            "id": "81bd870a6b39e722",
            "type": "leaf",
            "state": {
              "type": "markdown",
              "state": {
                "file": "H-每日记录/2024-04-20.md",
                "mode": "source",
                "backlinks": false,
                "source": false
              }
            }
          },
          {
            "id": "f63635129baea939",
            "type": "leaf",
            "state": {
              "type": "markdown",
              "state": {
                "file": "Vue.js 3.0企业级管理后台开发实战/Vue.js 3.0企业级管理后台开发实战：基于Element Plus.md",
                "mode": "source",
                "backlinks": false,
                "source": false
              }
            }
          },
          {
            "id": "01e71d60e7c16906",
            "type": "leaf",
            "state": {
              "type": "markdown",
              "state": {
                "file": "Vue.js 3.0企业级管理后台开发实战/项目构建.md",
                "mode": "source",
                "backlinks": false,
                "source": false
              }
            }
          },
          {
            "id": "a854ee4cdb8ef93f",
            "type": "leaf",
            "state": {
              "type": "markdown",
              "state": {
                "file": "Vue.js 3.0企业级管理后台开发实战/Vue.js 3.0企业级管理后台开发实战：基于Element Plus.md",
                "mode": "source",
                "backlinks": false,
                "source": false
              }
            }
          },
          {
            "id": "591a26d604f7da84",
            "type": "leaf",
            "state": {
              "type": "markdown",
              "state": {
                "file": "Vue.js 3.0企业级管理后台开发实战/3.6 项目初始化配置.md",
                "mode": "source",
                "backlinks": false,
                "source": false
              }
            }
          }
        ],
        "currentTab": 13
      }
    ],
    "direction": "vertical"
  },
  "left": {
    "id": "d6e132846ea5303e",
    "type": "split",
    "children": [
      {
        "id": "e6cd1d46bbe9c01b",
        "type": "tabs",
        "children": [
          {
            "id": "71428dd1d5256ed5",
            "type": "leaf",
            "state": {
              "type": "search",
              "state": {
                "query": "",
                "matchingCase": true,
                "explainSearch": false,
                "collapseAll": false,
                "extraContext": false,
                "sortOrder": "alphabeticalReverse"
              }
            }
          },
          {
            "id": "1f1c718126619a98",
            "type": "leaf",
            "state": {
              "type": "file-explorer",
              "state": {
                "sortOrder": "alphabetical"
              }
            }
          },
          {
            "id": "7038bf0f824d815a",
            "type": "leaf",
            "state": {
              "type": "recent-files",
              "state": {}
            }
          },
          {
            "id": "04bcd9f5c94c8348",
            "type": "leaf",
            "state": {
              "type": "bookmarks",
              "state": {}
            }
          }
        ],
        "currentTab": 1
      }
    ],
    "direction": "horizontal",
    "width": 268.5
  },
  "right": {
    "id": "4c275809f335b52b",
    "type": "split",
    "children": [
      {
        "id": "f51087a759ff49fc",
        "type": "tabs",
        "children": [
          {
            "id": "d04be78bd53daa5b",
            "type": "leaf",
            "state": {
              "type": "outline",
              "state": {
                "file": "Vue.js 3.0企业级管理后台开发实战/3.6 项目初始化配置.md"
              }
            }
          },
          {
            "id": "c6064d0fc211579d",
            "type": "leaf",
            "state": {
              "type": "outgoing-link",
              "state": {
                "file": "Vue.js 3.0企业级管理后台开发实战/3.6 项目初始化配置.md",
                "linksCollapsed": false,
                "unlinkedCollapsed": true
              }
            }
          },
          {
            "id": "1be96e87defd3e79",
            "type": "leaf",
            "state": {
              "type": "backlink",
              "state": {
                "file": "Vue.js 3.0企业级管理后台开发实战/3.6 项目初始化配置.md",
                "collapseAll": false,
                "extraContext": false,
                "sortOrder": "alphabetical",
                "showSearch": false,
                "searchQuery": "",
                "backlinkCollapsed": false,
                "unlinkedCollapsed": true
              }
            }
          }
        ]
      }
    ],
    "direction": "horizontal",
    "width": 200,
    "collapsed": true
  },
  "left-ribbon": {
    "hiddenItems": {
      "switcher:打开快速切换": false,
      "command-palette:打开命令面板": false,
      "templates:插入模板": false,
      "daily-notes:打开/创建今天的日记": false,
      "obsidian42-brat:BRAT": false,
      "templater-obsidian:Templater": false,
      "graph:查看关系图谱": false
    }
  },
  "active": "591a26d604f7da84",
  "lastOpenFiles": [
    "代码/Vue.js 3.0企业级管理后台开发实战/vue3-element-plus-admin-main/node_modules/@floating-ui/utils/dist/floating-ui.utils.umd.min.js",
    "代码/Vue.js 3.0企业级管理后台开发实战/vue3-element-plus-admin-main/node_modules/@floating-ui/utils/dist/floating-ui.utils.umd.js",
    "代码/Vue.js 3.0企业级管理后台开发实战/vue3-element-plus-admin-main/node_modules/@floating-ui/utils/dist/floating-ui.utils.mjs",
    "代码/Vue.js 3.0企业级管理后台开发实战/vue3-element-plus-admin-main/node_modules/@floating-ui/utils/dist/floating-ui.utils.dom.umd.min.js",
    "代码/Vue.js 3.0企业级管理后台开发实战/vue3-element-plus-admin-main/node_modules/@floating-ui/utils/dist/floating-ui.utils.esm.js",
    "代码/Vue.js 3.0企业级管理后台开发实战/vue3-element-plus-admin-main/node_modules/@floating-ui/utils/dist/floating-ui.utils.dom.umd.js",
    "代码/Vue.js 3.0企业级管理后台开发实战/vue3-element-plus-admin-main/node_modules/@floating-ui/utils/dist/floating-ui.utils.dom.mjs",
    "代码/Vue.js 3.0企业级管理后台开发实战/vue3-element-plus-admin-main/node_modules/@floating-ui/utils/dist/floating-ui.utils.dom.esm.js",
    "代码/Vue.js 3.0企业级管理后台开发实战/vue3-element-plus-admin-main/node_modules/@floating-ui/utils/dist/floating-ui.utils.dom.d.ts",
    "代码/Vue.js 3.0企业级管理后台开发实战/vue3-element-plus-admin-main/node_modules/@floating-ui/utils/dist/floating-ui.utils.dom.d.mts",
    "代码/Vue.js 3.0企业级管理后台开发实战/vue3-element-plus-admin-main/node_modules/@floating-ui/utils/dist/floating-ui.utils.dom.browser.mjs",
    "代码/Vue.js 3.0企业级管理后台开发实战/vue3-element-plus-admin-main/node_modules/@vueuse/shared/node_modules/vue-demi/README.md",
    "代码/Vue.js 3.0企业级管理后台开发实战/vue3-element-plus-admin-main/node_modules/@vueuse/core/node_modules/vue-demi/README.md",
    "Vue.js 3.0企业级管理后台开发实战/Vue.js 3.0企业级管理后台开发实战：基于Element Plus.md",
    "Vue.js 3.0企业级管理后台开发实战/3.6 项目初始化配置.md",
    "19-工具类/vscode插件/未命名.md",
    "19-工具类/vscode插件/Vue VSCode Snippets.md",
    "H-每日记录/2024-04-20.md",
    "代码/Vue.js 3.0企业级管理后台开发实战/vue3-element-plus-admin-main/node_modules/vuex/README.md",
    "代码/Vue.js 3.0企业级管理后台开发实战/vue3-element-plus-admin-main/node_modules/vuex/CHANGELOG.md",
    "代码/Vue.js 3.0企业级管理后台开发实战/vue3-element-plus-admin-main/node_modules/vue-router/README.md",
    "代码/Vue.js 3.0企业级管理后台开发实战/vue3-element-plus-admin-main/node_modules/immutable/README.md",
    "代码/Vue.js 3.0企业级管理后台开发实战/vue3-element-plus-admin-main/node_modules/sass/README.md",
    "代码/Vue.js 3.0企业级管理后台开发实战/vue3-element-plus-admin-main/node_modules/html-entities/README.md",
    "代码/Vue.js 3.0企业级管理后台开发实战/vue3-element-plus-admin-main/node_modules/postcss-modules-extract-imports/README.md",
    "代码/Vue.js 3.0企业级管理后台开发实战/vue3-element-plus-admin-main/node_modules/postcss-modules-extract-imports/CHANGELOG.md",
    "代码/Vue.js 3.0企业级管理后台开发实战/vue3-element-plus-admin-main/node_modules/convert-source-map/README.md",
    "代码/Vue.js 3.0企业级管理后台开发实战/vue3-element-plus-admin-main/node_modules/events/security.md",
    "代码/Vue.js 3.0企业级管理后台开发实战/vue3-element-plus-admin-main/node_modules/events/Readme.md",
    "代码/Vue.js 3.0企业级管理后台开发实战/vue3-element-plus-admin-main/node_modules/events/History.md",
    "代码/Vue.js 3.0企业级管理后台开发实战/vue3-element-plus-admin-main/node_modules/schema-utils/README.md",
    "代码/Vue.js 3.0企业级管理后台开发实战/vue3-element-plus-admin-main/node_modules/schema-utils/CHANGELOG.md",
    "代码/Vue.js 3.0企业级管理后台开发实战/vue3-element-plus-admin-main/node_modules/emojis-list/README.md",
    "代码/Vue.js 3.0企业级管理后台开发实战/vue3-element-plus-admin-main/node_modules/emojis-list/LICENSE.md",
    "代码/Vue.js 3.0企业级管理后台开发实战/vue3-element-plus-admin-main/node_modules/emojis-list/CHANGELOG.md",
    "代码/Vue.js 3.0企业级管理后台开发实战/vue3-element-plus-admin-main/node_modules/whatwg-fetch/README.md",
    "代码/Vue.js 3.0企业级管理后台开发实战/vue3-element-plus-admin-main/node_modules/dotenv-expand/dotenv-expand.png",
    "代码/Vue.js 3.0企业级管理后台开发实战/vue3-element-plus-admin-main/node_modules/serve-index/public/icons/page_world.png",
    "代码/Vue.js 3.0企业级管理后台开发实战/vue3-element-plus-admin-main/node_modules/serve-index/public/icons/page_word.png",
    "代码/Vue.js 3.0企业级管理后台开发实战/vue3-element-plus-admin-main/node_modules/serve-index/public/icons/page_white_zip.png",
    "代码/Vue.js 3.0企业级管理后台开发实战/vue3-element-plus-admin-main/node_modules/serve-index/public/icons/page_white_wrench.png",
    "代码/Vue.js 3.0企业级管理后台开发实战/vue3-element-plus-admin-main/node_modules/serve-index/public/icons/page_white_world.png",
    "代码/Vue.js 3.0企业级管理后台开发实战/vue3-element-plus-admin-main/node_modules/serve-index/public/icons/page_white_word.png",
    "代码/Vue.js 3.0企业级管理后台开发实战/vue3-element-plus-admin-main/node_modules/serve-index/public/icons/page_white_width.png",
    "代码/Vue.js 3.0企业级管理后台开发实战/vue3-element-plus-admin-main/node_modules/serve-index/public/icons/page_white_visualstudio.png",
    "代码/Vue.js 3.0企业级管理后台开发实战/vue3-element-plus-admin-main/node_modules/serve-index/public/icons/page_white_vector.png"
  ]
}